MANIFEST.in
README.txt
setup.cfg
setup.py
asv_files/__init__.py
asv_files/settings.py
asv_files.egg-info/PKG-INFO
asv_files.egg-info/SOURCES.txt
asv_files.egg-info/dependency_links.txt
asv_files.egg-info/not-zip-safe
asv_files.egg-info/requires.txt
asv_files.egg-info/top_level.txt
asv_files/common/__init__.py
asv_files/dj/__init__.py
asv_files/dj/admin.py
asv_files/dj/fields.py
asv_files/dj/models.py
asv_files/dj/settings.py
asv_files/dj/urls.py
asv_files/dj/utils.py
asv_files/dj/views.py
asv_files/dj/management/__init__.py
asv_files/dj/management/commands/__init__.py
asv_files/dj/management/commands/uploads.py
asv_files/dj/static/asv_files/img/loading1.gif
asv_files/dj/static/asv_files/img/loading2.gif
asv_files/dj/static/asv_files/img/loading3.gif
asv_files/dj/static/asv_files/js/ctfiles_formfield_widget.js
asv_files/dj/templates/asv_files__admin__file_preview.html
asv_files/dj/templates/asv_files__admin__stacked.html
asv_files/dj/templates/asv_files/ctfiles_field_formwidget.html
asv_files/dj/templatetags/__init__.py
asv_files/dj/templatetags/asv_files_tags.py
asv_files/flask/__init__.py
asv_files/gae/__init__.py