Metadata-Version: 1.0
Name: asv-files
Version: dev-20121101-01
Summary: Module for:
